LICENSE.txt
README.txt
setup.py
Byecap.egg-info/PKG-INFO
Byecap.egg-info/SOURCES.txt
Byecap.egg-info/dependency_links.txt
Byecap.egg-info/top_level.txt
hcaptcha/__init__.py
hcaptcha/challenges.py
hcaptcha/constants.py
hcaptcha/exceptions.py
hcaptcha/startup.py
hcaptcha/structures.py
hcaptcha/utils.py
hcaptcha/agents/__init__.py
hcaptcha/agents/base.py
hcaptcha/agents/chrome.py
hcaptcha/curves/__init__.py
hcaptcha/curves/_beziercurve.py
hcaptcha/curves/_utils.py
hcaptcha/curves/humancurve.py
hcaptcha/http_/__init__.py
hcaptcha/http_/clients.py
hcaptcha/http_/utils.py
hcaptcha/models/__init__.py
hcaptcha/models/tiles.py
hcaptcha/proofs/__init__.py
hcaptcha/proofs/hsl.py
hcaptcha/proofs/hsw.py
hcaptcha/proofs/old.py
hcaptcha/solving/__init__.py
hcaptcha/solving/exceptions.py
hcaptcha/solving/solvers.py